litedoc-0.1.0.dev20241214103637.dist-info/METADATA
litedoc-0.1.0.dev20241214103637.dist-info/WHEEL
litedoc-0.1.0.dev20241214103637.dist-info/entry_points.txt
litedoc-0.1.0.dev20241214103637.dist-info/licenses/LICENSE
litedoc/__init__.py
litedoc/__main__.py
litedoc/docstring/__init__.py
litedoc/docstring/docstring.py
litedoc/docstring/parser.py
litedoc/i18n.py
litedoc/output.py
litedoc/style/__init__.py
litedoc/style/markdown.py
litedoc/syntax/astparser.py
litedoc/syntax/node.py
litedoc/utils.py
litedoc/version.py
litedoc-0.1.0.dev20241214103637.dist-info/RECORD
