Metadata-Version: 2.1
Name: litedoc
Version: 0.1.0.dev20241214103637
Summary: Default template for PDM package
Author-Email: snowykami <snowykami@outlook.com>
License: MIT
Requires-Python: >=3.10
Requires-Dist: pydantic>=2.8.2
